FastaIndex.py
fasta_stats.py
FastaIndex-0.11rc7.dist-info/DESCRIPTION.rst
FastaIndex-0.11rc7.dist-info/METADATA
FastaIndex-0.11rc7.dist-info/RECORD
FastaIndex-0.11rc7.dist-info/WHEEL
FastaIndex-0.11rc7.dist-info/entry_points.txt
FastaIndex-0.11rc7.dist-info/metadata.json
FastaIndex-0.11rc7.dist-info/top_level.txt
