Metadata-Version: 2.0
Name: FastaIndex
Version: 0.11rc7
Summary: UNKNOWN
Home-page: https://github.com/lpryszcz/FastaIndex
Author: Leszek Pryszcz
Author-email: l.p.pryszcz+distutils@gmail.com
License: GPLv2
Keywords: FastA indexing stats N50 N90
Platform: UNKNOWN
Classifier: Development Status :: 4 - Beta
Classifier: Programming Language :: Python :: 2
Classifier: Programming Language :: Python :: 2.7
